WuaiPojieLuntanjinghuaJi2016/README.md
WuaiPojieLuntanjinghuaJi2016/__init__.py
WuaiPojieLuntanjinghuaJi2016/__main__.py
WuaiPojieLuntanjinghuaJi2016/file.epub
WuaiPojieLuntanjinghuaJi2016/index.html
WuaiPojieLuntanjinghuaJi2016/css/__init__.py
WuaiPojieLuntanjinghuaJi2016/css/annotations.css
WuaiPojieLuntanjinghuaJi2016/css/main.css
WuaiPojieLuntanjinghuaJi2016/css/normalize.css
WuaiPojieLuntanjinghuaJi2016/css/popup.css
WuaiPojieLuntanjinghuaJi2016/font/__init__.py
WuaiPojieLuntanjinghuaJi2016/font/fontello.eot
WuaiPojieLuntanjinghuaJi2016/font/fontello.svg
WuaiPojieLuntanjinghuaJi2016/font/fontello.ttf
WuaiPojieLuntanjinghuaJi2016/font/fontello.woff
WuaiPojieLuntanjinghuaJi2016/img/__init__.py
WuaiPojieLuntanjinghuaJi2016/img/annotator-glyph-sprite.png
WuaiPojieLuntanjinghuaJi2016/img/annotator-icon-sprite.png
WuaiPojieLuntanjinghuaJi2016/img/apple-touch-icon.png
WuaiPojieLuntanjinghuaJi2016/img/cancelfullscreen.png
WuaiPojieLuntanjinghuaJi2016/img/close.png
WuaiPojieLuntanjinghuaJi2016/img/fullscreen.png
WuaiPojieLuntanjinghuaJi2016/img/loader.gif
WuaiPojieLuntanjinghuaJi2016/img/menu-icon.png
WuaiPojieLuntanjinghuaJi2016/img/save.png
WuaiPojieLuntanjinghuaJi2016/img/saved.png
WuaiPojieLuntanjinghuaJi2016/img/settings-s.png
WuaiPojieLuntanjinghuaJi2016/img/settings.png
WuaiPojieLuntanjinghuaJi2016/img/star.png
WuaiPojieLuntanjinghuaJi2016/js/__init__.py
WuaiPojieLuntanjinghuaJi2016/js/epub.js
WuaiPojieLuntanjinghuaJi2016/js/epub.min.js
WuaiPojieLuntanjinghuaJi2016/js/epub.min.map
WuaiPojieLuntanjinghuaJi2016/js/hooks.min.js
WuaiPojieLuntanjinghuaJi2016/js/hooks.min.map
WuaiPojieLuntanjinghuaJi2016/js/reader.js
WuaiPojieLuntanjinghuaJi2016/js/reader.js.map
WuaiPojieLuntanjinghuaJi2016/js/reader.min.js
WuaiPojieLuntanjinghuaJi2016/js/reader.min.map
WuaiPojieLuntanjinghuaJi2016/js/hooks/__init__.py
WuaiPojieLuntanjinghuaJi2016/js/hooks/extensions/__init__.py
WuaiPojieLuntanjinghuaJi2016/js/hooks/extensions/highlight.js
wuai_pojie_luntanjinghua_ji_2016-2024.3.5.0.dist-info/METADATA
wuai_pojie_luntanjinghua_ji_2016-2024.3.5.0.dist-info/WHEEL
wuai_pojie_luntanjinghua_ji_2016-2024.3.5.0.dist-info/entry_points.txt
wuai_pojie_luntanjinghua_ji_2016-2024.3.5.0.dist-info/top_level.txt
wuai_pojie_luntanjinghua_ji_2016-2024.3.5.0.dist-info/RECORD
